jupyter_projector_proxy/__init__.py
jupyter_projector_proxy/icons/pycharm.svg
jupyter_projector_proxy-1.0.9.dist-info/LICENSE.md
jupyter_projector_proxy-1.0.9.dist-info/METADATA
jupyter_projector_proxy-1.0.9.dist-info/WHEEL
jupyter_projector_proxy-1.0.9.dist-info/entry_points.txt
jupyter_projector_proxy-1.0.9.dist-info/top_level.txt
jupyter_projector_proxy-1.0.9.dist-info/RECORD
