Metadata-Version: 2.1
Name: jupyter-projector-proxy
Version: 1.0.9
Summary: Jupyter extension to proxy Jetbrains IDEs
Home-page: https://github.com/tiaden/jupyter-projector-proxy
Author: Edem Tiassou
Author-email: workmail.edem@gmail.com
License: MIT LICENSE
Keywords: Jupyter,Jupyter Proxy,Jupyter Server Proxy,Jetbrains,IntelliJ,PyCharm,DataGrip,WebStorm,Goland,Clion,PhpStorm,RubyMine
Classifier: Framework :: Jupyter
Classifier: Intended Audience :: Developers
Classifier: Natural Language :: English
Classifier: Programming Language :: Python
Classifier: Programming Language :: Python :: 3.8
Classifier: Programming Language :: Python :: 3.9
Classifier: Programming Language :: Python :: 3.10
Requires-Python: ~=3.8
License-File: LICENSE.md
Requires-Dist: jupyter-server-proxy
